pretty_doc/__init__.py
pretty_doc-0.3.dist-info/LICENSE
pretty_doc-0.3.dist-info/METADATA
pretty_doc-0.3.dist-info/WHEEL
pretty_doc-0.3.dist-info/top_level.txt
pretty_doc-0.3.dist-info/RECORD
