Metadata-Version: 2.1
Name: pretty-doc
Version: 0.3
Summary: A simple document rendering system in Python
Home-page: https://github.com/thautwarm/pretty-doc
Author: thautwarm
Author-email: twshere@outlook.com
License: mit
Keywords: pretty print,doc object,composable text objects
Platform: any
Classifier: Programming Language :: Python :: 3.6
Classifier: Programming Language :: Python :: 3.7
Classifier: Programming Language :: Python :: 3.8
Classifier: Programming Language :: Python :: 3.9
Classifier: Programming Language :: Python :: 3.10
Classifier: Programming Language :: Python :: 3.11
Classifier: Programming Language :: Python :: Implementation :: CPython
Classifier: Programming Language :: Python :: Implementation :: PyPy
Requires-Python: >=3.6.0
License-File: LICENSE
Requires-Dist: dataclasses ; python_version < "3.7"
